{"stock":"0020.XHKG_closeDelta1dR","score":1.0,"params":{"copy_X":true,"fit_intercept":true,"n_jobs":null,"normalize":false,"positive":false},"custom_training_error_sum":2.048873815e-27,"custom_training_error":0.0}
{"stock":"0020.XHKG_closeDelta2dR","score":1.0,"params":{"copy_X":true,"fit_intercept":true,"n_jobs":null,"normalize":false,"positive":false},"custom_training_error_sum":1.771036716e-27,"custom_training_error":0.0}
{"stock":"0020.XHKG_closeDelta3dR","score":1.0,"params":{"copy_X":true,"fit_intercept":true,"n_jobs":null,"normalize":false,"positive":false},"custom_training_error_sum":2.023355624e-27,"custom_training_error":0.0}
{"stock":"0020.XHKG_closeDelta4dR","score":1.0,"params":{"copy_X":true,"fit_intercept":true,"n_jobs":null,"normalize":false,"positive":false},"custom_training_error_sum":1.621758547e-27,"custom_training_error":0.0}
{"stock":"0020.XHKG_closeDelta5dR","score":1.0,"params":{"copy_X":true,"fit_intercept":true,"n_jobs":null,"normalize":false,"positive":false},"custom_training_error_sum":1.531212324e-27,"custom_training_error":0.0}
{"stock":"0020.XHKG_closeDelta6dR","score":1.0,"params":{"copy_X":true,"fit_intercept":true,"n_jobs":null,"normalize":false,"positive":false},"custom_training_error_sum":1.883246299e-27,"custom_training_error":0.0}
{"stock":"0020.XHKG_closeDelta7dR","score":1.0,"params":{"copy_X":true,"fit_intercept":true,"n_jobs":null,"normalize":false,"positive":false},"custom_training_error_sum":1.588821739e-27,"custom_training_error":0.0}
{"stock":"0020.XHKG_closeDelta8dR","score":1.0,"params":{"copy_X":true,"fit_intercept":true,"n_jobs":null,"normalize":false,"positive":false},"custom_training_error_sum":1.67730981e-27,"custom_training_error":0.0}
{"stock":"0020.XHKG_closeDelta9dR","score":1.0,"params":{"copy_X":true,"fit_intercept":true,"n_jobs":null,"normalize":false,"positive":false},"custom_training_error_sum":1.545774957e-27,"custom_training_error":0.0}
{"stock":"0175.XHKG_closeDelta2dR","score":1.0,"params":{"copy_X":true,"fit_intercept":true,"n_jobs":null,"normalize":false,"positive":false},"custom_training_error_sum":3.404378393e-27,"custom_training_error":0.0}
{"stock":"0291.XHKG_closeDelta5dR","score":1.0,"params":{"copy_X":true,"fit_intercept":true,"n_jobs":null,"normalize":false,"positive":false},"custom_training_error_sum":2.754508451e-27,"custom_training_error":0.0}
{"stock":"0016.XHKG_closeDelta9dR","score":1.0,"params":{"copy_X":true,"fit_intercept":true,"n_jobs":null,"normalize":false,"positive":false},"custom_training_error_sum":1.419068661e-27,"custom_training_error":0.0}
{"stock":"0388.XHKG_closeDelta6dR","score":1.0,"params":{"copy_X":true,"fit_intercept":true,"n_jobs":null,"normalize":false,"positive":false},"custom_training_error_sum":1.677556373e-27,"custom_training_error":0.0}
{"stock":"1038.XHKG_closeDelta3dR","score":1.0,"params":{"copy_X":true,"fit_intercept":true,"n_jobs":null,"normalize":false,"positive":false},"custom_training_error_sum":1.497161316e-27,"custom_training_error":0.0}
{"stock":"1918.XHKG_closeDelta7dR","score":1.0,"params":{"copy_X":true,"fit_intercept":true,"n_jobs":null,"normalize":false,"positive":false},"custom_training_error_sum":3.995903048e-27,"custom_training_error":0.0}
{"stock":"2202.XHKG_closeDelta8dR","score":1.0,"params":{"copy_X":true,"fit_intercept":true,"n_jobs":null,"normalize":false,"positive":false},"custom_training_error_sum":4.822884808e-27,"custom_training_error":0.0}
{"stock":"6186.XHKG_closeDelta2dR","score":1.0,"params":{"copy_X":true,"fit_intercept":true,"n_jobs":null,"normalize":false,"positive":false},"custom_training_error_sum":1.564363205e-27,"custom_training_error":0.0}
{"stock":"6288.XHKG_closeDelta5dR","score":1.0,"params":{"copy_X":true,"fit_intercept":true,"n_jobs":null,"normalize":false,"positive":false},"custom_training_error_sum":3.024724142e-27,"custom_training_error":0.0}
{"stock":"0939.XHKG_closeDelta2dR","score":1.0,"params":{"copy_X":true,"fit_intercept":true,"n_jobs":null,"normalize":false,"positive":false},"custom_training_error_sum":3.028396462e-27,"custom_training_error":0.0}
{"stock":"6288.XHKG_closeDelta9dR","score":1.0,"params":{"copy_X":true,"fit_intercept":true,"n_jobs":null,"normalize":false,"positive":false},"custom_training_error_sum":5.156286415e-27,"custom_training_error":0.0}
{"stock":"0012.XHKG_closeDelta4dR","score":1.0,"params":{"copy_X":true,"fit_intercept":true,"n_jobs":null,"normalize":false,"positive":false},"custom_training_error_sum":1.883187324e-27,"custom_training_error":0.0}
{"stock":"0388.XHKG_closeDelta1dR","score":1.0,"params":{"copy_X":true,"fit_intercept":true,"n_jobs":null,"normalize":false,"positive":false},"custom_training_error_sum":2.434727664e-27,"custom_training_error":0.0}
{"stock":"2007.XHKG_closeDelta1dR","score":1.0,"params":{"copy_X":true,"fit_intercept":true,"n_jobs":null,"normalize":false,"positive":false},"custom_training_error_sum":2.862667317e-27,"custom_training_error":0.0}
{"stock":"2269.XHKG_closeDelta3dR","score":1.0,"params":{"copy_X":true,"fit_intercept":true,"n_jobs":null,"normalize":false,"positive":false},"custom_training_error_sum":4.472118732e-27,"custom_training_error":0.0}
{"stock":"2319.XHKG_closeDelta7dR","score":1.0,"params":{"copy_X":true,"fit_intercept":true,"n_jobs":null,"normalize":false,"positive":false},"custom_training_error_sum":2.596896755e-27,"custom_training_error":0.0}
{"stock":"6862.XHKG_closeDelta7dR","score":1.0,"params":{"copy_X":true,"fit_intercept":true,"n_jobs":null,"normalize":false,"positive":false},"custom_training_error_sum":2.242580853e-27,"custom_training_error":0.0}
{"stock":"2628.XHKG_closeDelta2dR","score":1.0,"params":{"copy_X":true,"fit_intercept":true,"n_jobs":null,"normalize":false,"positive":false},"custom_training_error_sum":2.894623505e-27,"custom_training_error":0.0}
{"stock":"0288.XHKG_closeDelta4dR","score":1.0,"params":{"copy_X":true,"fit_intercept":true,"n_jobs":null,"normalize":false,"positive":false},"custom_training_error_sum":1.962079819e-27,"custom_training_error":0.0}
{"stock":"1816.XHKG_closeDelta9dR","score":1.0,"params":{"copy_X":true,"fit_intercept":true,"n_jobs":null,"normalize":false,"positive":false},"custom_training_error_sum":4.401543876e-27,"custom_training_error":0.0}
{"stock":"9988.XHKG_closeDelta4dR","score":1.0,"params":{"copy_X":true,"fit_intercept":true,"n_jobs":null,"normalize":false,"positive":false},"custom_training_error_sum":2.359834727e-27,"custom_training_error":0.0}
{"stock":"0175.XHKG_closeDelta5dR","score":1.0,"params":{"copy_X":true,"fit_intercept":true,"n_jobs":null,"normalize":false,"positive":false},"custom_training_error_sum":3.95721856e-27,"custom_training_error":0.0}
{"stock":"0006.XHKG_closeDelta3dR","score":1.0,"params":{"copy_X":true,"fit_intercept":true,"n_jobs":null,"normalize":false,"positive":false},"custom_training_error_sum":1.408437889e-27,"custom_training_error":0.0}
{"stock":"0700.XHKG_closeDelta3dR","score":1.0,"params":{"copy_X":true,"fit_intercept":true,"n_jobs":null,"normalize":false,"positive":false},"custom_training_error_sum":2.197965106e-27,"custom_training_error":0.0}
{"stock":"1398.XHKG_closeDelta5dR","score":1.0,"params":{"copy_X":true,"fit_intercept":true,"n_jobs":null,"normalize":false,"positive":false},"custom_training_error_sum":4.947328011e-27,"custom_training_error":0.0}
{"stock":"0788.XHKG_closeDelta2dR","score":1.0,"params":{"copy_X":true,"fit_intercept":true,"n_jobs":null,"normalize":false,"positive":false},"custom_training_error_sum":3.151580591e-27,"custom_training_error":0.0}
{"stock":"3333.XHKG_closeDelta7dR","score":1.0,"params":{"copy_X":true,"fit_intercept":true,"n_jobs":null,"normalize":false,"positive":false},"custom_training_error_sum":1.789694671e-27,"custom_training_error":0.0}
{"stock":"0012.XHKG_closeDelta9dR","score":1.0,"params":{"copy_X":true,"fit_intercept":true,"n_jobs":null,"normalize":false,"positive":false},"custom_training_error_sum":1.844474958e-27,"custom_training_error":0.0}
{"stock":"0763.XHKG_closeDelta4dR","score":1.0,"params":{"copy_X":true,"fit_intercept":true,"n_jobs":null,"normalize":false,"positive":false},"custom_training_error_sum":3.178906331e-27,"custom_training_error":0.0}
{"stock":"0945.XHKG_closeDelta2dR","score":1.0,"params":{"copy_X":true,"fit_intercept":true,"n_jobs":null,"normalize":false,"positive":false},"custom_training_error_sum":1.786057651e-27,"custom_training_error":0.0}
{"stock":"0857.XHKG_closeDelta5dR","score":1.0,"params":{"copy_X":true,"fit_intercept":true,"n_jobs":null,"normalize":false,"positive":false},"custom_training_error_sum":1.927207732e-27,"custom_training_error":0.0}
{"stock":"0288.XHKG_closeDelta2dR","score":1.0,"params":{"copy_X":true,"fit_intercept":true,"n_jobs":null,"normalize":false,"positive":false},"custom_training_error_sum":2.035427391e-27,"custom_training_error":0.0}
{"stock":"1766.XHKG_closeDelta2dR","score":1.0,"params":{"copy_X":true,"fit_intercept":true,"n_jobs":null,"normalize":false,"positive":false},"custom_training_error_sum":2.775091174e-27,"custom_training_error":0.0}
{"stock":"3968.XHKG_closeDelta1dR","score":1.0,"params":{"copy_X":true,"fit_intercept":true,"n_jobs":null,"normalize":false,"positive":false},"custom_training_error_sum":3.034326774e-27,"custom_training_error":0.0}
{"stock":"1288.XHKG_closeDelta2dR","score":1.0,"params":{"copy_X":true,"fit_intercept":true,"n_jobs":null,"normalize":false,"positive":false},"custom_training_error_sum":2.859051428e-27,"custom_training_error":0.0}
{"stock":"2313.XHKG_closeDelta3dR","score":1.0,"params":{"copy_X":true,"fit_intercept":true,"n_jobs":null,"normalize":false,"positive":false},"custom_training_error_sum":1.617125623e-27,"custom_training_error":0.0}
{"stock":"1113.XHKG_closeDelta3dR","score":1.0,"params":{"copy_X":true,"fit_intercept":true,"n_jobs":null,"normalize":false,"positive":false},"custom_training_error_sum":1.659840153e-27,"custom_training_error":0.0}
{"stock":"1876.XHKG_closeDelta5dR","score":1.0,"params":{"copy_X":true,"fit_intercept":true,"n_jobs":null,"normalize":false,"positive":false},"custom_training_error_sum":1.370542184e-27,"custom_training_error":0.0}
{"stock":"2318.XHKG_closeDelta9dR","score":1.0,"params":{"copy_X":true,"fit_intercept":true,"n_jobs":null,"normalize":false,"positive":false},"custom_training_error_sum":4.038403801e-27,"custom_training_error":0.0}
{"stock":"2611.XHKG_closeDelta7dR","score":1.0,"params":{"copy_X":true,"fit_intercept":true,"n_jobs":null,"normalize":false,"positive":false},"custom_training_error_sum":5.018983796e-27,"custom_training_error":0.0}
{"stock":"3690.XHKG_closeDelta1dR","score":1.0,"params":{"copy_X":true,"fit_intercept":true,"n_jobs":null,"normalize":false,"positive":false},"custom_training_error_sum":2.615192982e-27,"custom_training_error":0.0}
{"stock":"0175.XHKG_closeDelta7dR","score":1.0,"params":{"copy_X":true,"fit_intercept":true,"n_jobs":null,"normalize":false,"positive":false},"custom_training_error_sum":4.093787154e-27,"custom_training_error":0.0}
{"stock":"2611.XHKG_closeDelta9dR","score":1.0,"params":{"copy_X":true,"fit_intercept":true,"n_jobs":null,"normalize":false,"positive":false},"custom_training_error_sum":5.919120298e-27,"custom_training_error":0.0}
{"stock":"1810.XHKG_closeDelta3dR","score":1.0,"params":{"copy_X":true,"fit_intercept":true,"n_jobs":null,"normalize":false,"positive":false},"custom_training_error_sum":1.662108212e-27,"custom_training_error":0.0}
{"stock":"0688.XHKG_closeDelta2dR","score":1.0,"params":{"copy_X":true,"fit_intercept":true,"n_jobs":null,"normalize":false,"positive":false},"custom_training_error_sum":2.598919053e-27,"custom_training_error":0.0}
{"stock":"0006.XHKG_closeDelta4dR","score":1.0,"params":{"copy_X":true,"fit_intercept":true,"n_jobs":null,"normalize":false,"positive":false},"custom_training_error_sum":1.606908015e-27,"custom_training_error":0.0}
{"stock":"3690.XHKG_closeDelta6dR","score":1.0,"params":{"copy_X":true,"fit_intercept":true,"n_jobs":null,"normalize":false,"positive":false},"custom_training_error_sum":2.162721325e-27,"custom_training_error":0.0}
{"stock":"6186.XHKG_closeDelta3dR","score":1.0,"params":{"copy_X":true,"fit_intercept":true,"n_jobs":null,"normalize":false,"positive":false},"custom_training_error_sum":1.386769674e-27,"custom_training_error":0.0}
{"stock":"6808.XHKG_closeDelta3dR","score":1.0,"params":{"copy_X":true,"fit_intercept":true,"n_jobs":null,"normalize":false,"positive":false},"custom_training_error_sum":2.357764268e-27,"custom_training_error":0.0}
{"stock":"0267.XHKG_closeDelta5dR","score":1.0,"params":{"copy_X":true,"fit_intercept":true,"n_jobs":null,"normalize":false,"positive":false},"custom_training_error_sum":2.769181127e-27,"custom_training_error":0.0}
{"stock":"4335.XHKG_closeDelta6dR","score":1.0,"params":{"copy_X":true,"fit_intercept":true,"n_jobs":null,"normalize":false,"positive":false},"custom_training_error_sum":1.571088486e-27,"custom_training_error":0.0}
{"stock":"0019.XHKG_closeDelta4dR","score":1.0,"params":{"copy_X":true,"fit_intercept":true,"n_jobs":null,"normalize":false,"positive":false},"custom_training_error_sum":1.359871185e-27,"custom_training_error":0.0}
{"stock":"0291.XHKG_closeDelta3dR","score":1.0,"params":{"copy_X":true,"fit_intercept":true,"n_jobs":null,"normalize":false,"positive":false},"custom_training_error_sum":2.324011813e-27,"custom_training_error":0.0}
{"stock":"2388.XHKG_closeDelta4dR","score":1.0,"params":{"copy_X":true,"fit_intercept":true,"n_jobs":null,"normalize":false,"positive":false},"custom_training_error_sum":8.236772295e-28,"custom_training_error":0.0}
{"stock":"0941.XHKG_closeDelta6dR","score":1.0,"params":{"copy_X":true,"fit_intercept":true,"n_jobs":null,"normalize":false,"positive":false},"custom_training_error_sum":2.731769671e-27,"custom_training_error":0.0}
{"stock":"1339.XHKG_closeDelta5dR","score":1.0,"params":{"copy_X":true,"fit_intercept":true,"n_jobs":null,"normalize":false,"positive":false},"custom_training_error_sum":2.718968085e-27,"custom_training_error":0.0}
{"stock":"6030.XHKG_closeDelta8dR","score":1.0,"params":{"copy_X":true,"fit_intercept":true,"n_jobs":null,"normalize":false,"positive":false},"custom_training_error_sum":5.288723023e-27,"custom_training_error":0.0}
{"stock":"6837.XHKG_closeDelta2dR","score":1.0,"params":{"copy_X":true,"fit_intercept":true,"n_jobs":null,"normalize":false,"positive":false},"custom_training_error_sum":3.155015741e-27,"custom_training_error":0.0}
{"stock":"3968.XHKG_closeDelta4dR","score":1.0,"params":{"copy_X":true,"fit_intercept":true,"n_jobs":null,"normalize":false,"positive":false},"custom_training_error_sum":2.360288691e-27,"custom_training_error":0.0}
{"stock":"2378.XHKG_closeDelta4dR","score":1.0,"params":{"copy_X":true,"fit_intercept":true,"n_jobs":null,"normalize":false,"positive":false},"custom_training_error_sum":2.012854026e-27,"custom_training_error":0.0}
{"stock":"0016.XHKG_closeDelta8dR","score":1.0,"params":{"copy_X":true,"fit_intercept":true,"n_jobs":null,"normalize":false,"positive":false},"custom_training_error_sum":1.667122255e-27,"custom_training_error":0.0}
{"stock":"0003.XHKG_closeDelta9dR","score":1.0,"params":{"copy_X":true,"fit_intercept":true,"n_jobs":null,"normalize":false,"positive":false},"custom_training_error_sum":1.667538143e-27,"custom_training_error":0.0}
{"stock":"2020.XHKG_closeDelta5dR","score":1.0,"params":{"copy_X":true,"fit_intercept":true,"n_jobs":null,"normalize":false,"positive":false},"custom_training_error_sum":1.796184618e-27,"custom_training_error":0.0}
{"stock":"0288.XHKG_closeDelta5dR","score":1.0,"params":{"copy_X":true,"fit_intercept":true,"n_jobs":null,"normalize":false,"positive":false},"custom_training_error_sum":2.242763548e-27,"custom_training_error":0.0}
{"stock":"0386.XHKG_closeDelta6dR","score":1.0,"params":{"copy_X":true,"fit_intercept":true,"n_jobs":null,"normalize":false,"positive":false},"custom_training_error_sum":2.415214006e-27,"custom_training_error":0.0}
{"stock":"2338.XHKG_closeDelta8dR","score":1.0,"params":{"copy_X":true,"fit_intercept":true,"n_jobs":null,"normalize":false,"positive":false},"custom_training_error_sum":9.476433596e-28,"custom_training_error":0.0}
{"stock":"0700.XHKG_closeDelta5dR","score":1.0,"params":{"copy_X":true,"fit_intercept":true,"n_jobs":null,"normalize":false,"positive":false},"custom_training_error_sum":4.175847443e-27,"custom_training_error":0.0}
{"stock":"1186.XHKG_closeDelta3dR","score":1.0,"params":{"copy_X":true,"fit_intercept":true,"n_jobs":null,"normalize":false,"positive":false},"custom_training_error_sum":3.391829605e-27,"custom_training_error":0.0}
{"stock":"2007.XHKG_closeDelta5dR","score":1.0,"params":{"copy_X":true,"fit_intercept":true,"n_jobs":null,"normalize":false,"positive":false},"custom_training_error_sum":4.883862385e-27,"custom_training_error":0.0}
{"stock":"1336.XHKG_closeDelta1dR","score":1.0,"params":{"copy_X":true,"fit_intercept":true,"n_jobs":null,"normalize":false,"positive":false},"custom_training_error_sum":2.710829609e-27,"custom_training_error":0.0}
{"stock":"1339.XHKG_closeDelta8dR","score":1.0,"params":{"copy_X":true,"fit_intercept":true,"n_jobs":null,"normalize":false,"positive":false},"custom_training_error_sum":2.203690074e-27,"custom_training_error":0.0}
{"stock":"2338.XHKG_closeDelta6dR","score":1.0,"params":{"copy_X":true,"fit_intercept":true,"n_jobs":null,"normalize":false,"positive":false},"custom_training_error_sum":2.626150937e-27,"custom_training_error":0.0}
{"stock":"3692.XHKG_closeDelta5dR","score":1.0,"params":{"copy_X":true,"fit_intercept":true,"n_jobs":null,"normalize":false,"positive":false},"custom_training_error_sum":1.32614813e-27,"custom_training_error":0.0}
{"stock":"0388.XHKG_closeDelta9dR","score":1.0,"params":{"copy_X":true,"fit_intercept":true,"n_jobs":null,"normalize":false,"positive":false},"custom_training_error_sum":2.259034731e-27,"custom_training_error":0.0}
{"stock":"0001.XHKG_closeDelta3dR","score":1.0,"params":{"copy_X":true,"fit_intercept":true,"n_jobs":null,"normalize":false,"positive":false},"custom_training_error_sum":1.469240574e-27,"custom_training_error":0.0}
{"stock":"1928.XHKG_closeDelta1dR","score":1.0,"params":{"copy_X":true,"fit_intercept":true,"n_jobs":null,"normalize":false,"positive":false},"custom_training_error_sum":1.823382553e-27,"custom_training_error":0.0}
{"stock":"0762.XHKG_closeDelta4dR","score":1.0,"params":{"copy_X":true,"fit_intercept":true,"n_jobs":null,"normalize":false,"positive":false},"custom_training_error_sum":2.911885561e-27,"custom_training_error":0.0}
{"stock":"1398.XHKG_closeDelta8dR","score":1.0,"params":{"copy_X":true,"fit_intercept":true,"n_jobs":null,"normalize":false,"positive":false},"custom_training_error_sum":2.844880195e-27,"custom_training_error":0.0}
{"stock":"0388.XHKG_closeDelta7dR","score":1.0,"params":{"copy_X":true,"fit_intercept":true,"n_jobs":null,"normalize":false,"positive":false},"custom_training_error_sum":1.649844644e-27,"custom_training_error":0.0}
{"stock":"0267.XHKG_closeDelta6dR","score":1.0,"params":{"copy_X":true,"fit_intercept":true,"n_jobs":null,"normalize":false,"positive":false},"custom_training_error_sum":9.837140296e-28,"custom_training_error":0.0}
{"stock":"2359.XHKG_closeDelta5dR","score":1.0,"params":{"copy_X":true,"fit_intercept":true,"n_jobs":null,"normalize":false,"positive":false},"custom_training_error_sum":4.040798405e-27,"custom_training_error":0.0}
{"stock":"0763.XHKG_closeDelta6dR","score":1.0,"params":{"copy_X":true,"fit_intercept":true,"n_jobs":null,"normalize":false,"positive":false},"custom_training_error_sum":1.215630279e-27,"custom_training_error":0.0}
{"stock":"2269.XHKG_closeDelta6dR","score":1.0,"params":{"copy_X":true,"fit_intercept":true,"n_jobs":null,"normalize":false,"positive":false},"custom_training_error_sum":4.015000644e-27,"custom_training_error":0.0}
{"stock":"0813.XHKG_closeDelta6dR","score":1.0,"params":{"copy_X":true,"fit_intercept":true,"n_jobs":null,"normalize":false,"positive":false},"custom_training_error_sum":2.545897334e-27,"custom_training_error":0.0}
{"stock":"1177.XHKG_closeDelta8dR","score":1.0,"params":{"copy_X":true,"fit_intercept":true,"n_jobs":null,"normalize":false,"positive":false},"custom_training_error_sum":1.475072138e-27,"custom_training_error":0.0}
{"stock":"2313.XHKG_closeDelta2dR","score":1.0,"params":{"copy_X":true,"fit_intercept":true,"n_jobs":null,"normalize":false,"positive":false},"custom_training_error_sum":1.585965395e-27,"custom_training_error":0.0}
{"stock":"0388.XHKG_closeDelta3dR","score":1.0,"params":{"copy_X":true,"fit_intercept":true,"n_jobs":null,"normalize":false,"positive":false},"custom_training_error_sum":1.598455443e-27,"custom_training_error":0.0}
{"stock":"0003.XHKG_closeDelta4dR","score":1.0,"params":{"copy_X":true,"fit_intercept":true,"n_jobs":null,"normalize":false,"positive":false},"custom_training_error_sum":1.939642946e-27,"custom_training_error":0.0}
{"stock":"2313.XHKG_closeDelta8dR","score":1.0,"params":{"copy_X":true,"fit_intercept":true,"n_jobs":null,"normalize":false,"positive":false},"custom_training_error_sum":2.084193361e-27,"custom_training_error":0.0}
{"stock":"1088.XHKG_closeDelta4dR","score":1.0,"params":{"copy_X":true,"fit_intercept":true,"n_jobs":null,"normalize":false,"positive":false},"custom_training_error_sum":3.245778347e-27,"custom_training_error":0.0}
{"stock":"0700.XHKG_closeDelta7dR","score":1.0,"params":{"copy_X":true,"fit_intercept":true,"n_jobs":null,"normalize":false,"positive":false},"custom_training_error_sum":4.567794349e-27,"custom_training_error":0.0}
{"stock":"1800.XHKG_closeDelta9dR","score":1.0,"params":{"copy_X":true,"fit_intercept":true,"n_jobs":null,"normalize":false,"positive":false},"custom_training_error_sum":3.762414767e-27,"custom_training_error":0.0}
{"stock":"0241.XHKG_closeDelta5dR","score":1.0,"params":{"copy_X":true,"fit_intercept":true,"n_jobs":null,"normalize":false,"positive":false},"custom_training_error_sum":1.700384586e-27,"custom_training_error":0.0}
{"stock":"2601.XHKG_closeDelta5dR","score":1.0,"params":{"copy_X":true,"fit_intercept":true,"n_jobs":null,"normalize":false,"positive":false},"custom_training_error_sum":2.691347362e-27,"custom_training_error":0.0}
{"stock":"6862.XHKG_closeDelta9dR","score":1.0,"params":{"copy_X":true,"fit_intercept":true,"n_jobs":null,"normalize":false,"positive":false},"custom_training_error_sum":3.343707558e-27,"custom_training_error":0.0}
{"stock":"3333.XHKG_closeDelta9dR","score":1.0,"params":{"copy_X":true,"fit_intercept":true,"n_jobs":null,"normalize":false,"positive":false},"custom_training_error_sum":2.144543466e-27,"custom_training_error":0.0}
{"stock":"0384.XHKG_closeDelta4dR","score":1.0,"params":{"copy_X":true,"fit_intercept":true,"n_jobs":null,"normalize":false,"positive":false},"custom_training_error_sum":1.617426478e-27,"custom_training_error":0.0}
{"stock":"0386.XHKG_closeDelta3dR","score":1.0,"params":{"copy_X":true,"fit_intercept":true,"n_jobs":null,"normalize":false,"positive":false},"custom_training_error_sum":2.666163047e-27,"custom_training_error":0.0}
{"stock":"1658.XHKG_closeDelta3dR","score":1.0,"params":{"copy_X":true,"fit_intercept":true,"n_jobs":null,"normalize":false,"positive":false},"custom_training_error_sum":3.323150451e-27,"custom_training_error":0.0}
{"stock":"2318.XHKG_closeDelta5dR","score":1.0,"params":{"copy_X":true,"fit_intercept":true,"n_jobs":null,"normalize":false,"positive":false},"custom_training_error_sum":3.433431052e-27,"custom_training_error":0.0}
{"stock":"1177.XHKG_closeDelta7dR","score":1.0,"params":{"copy_X":true,"fit_intercept":true,"n_jobs":null,"normalize":false,"positive":false},"custom_training_error_sum":1.427349793e-27,"custom_training_error":0.0}
{"stock":"0288.XHKG_closeDelta3dR","score":1.0,"params":{"copy_X":true,"fit_intercept":true,"n_jobs":null,"normalize":false,"positive":false},"custom_training_error_sum":1.388752923e-27,"custom_training_error":0.0}
{"stock":"0960.XHKG_closeDelta6dR","score":1.0,"params":{"copy_X":true,"fit_intercept":true,"n_jobs":null,"normalize":false,"positive":false},"custom_training_error_sum":2.001036428e-27,"custom_training_error":0.0}
{"stock":"1093.XHKG_closeDelta3dR","score":1.0,"params":{"copy_X":true,"fit_intercept":true,"n_jobs":null,"normalize":false,"positive":false},"custom_training_error_sum":1.703712135e-27,"custom_training_error":0.0}
{"stock":"1988.XHKG_closeDelta7dR","score":1.0,"params":{"copy_X":true,"fit_intercept":true,"n_jobs":null,"normalize":false,"positive":false},"custom_training_error_sum":2.141348728e-27,"custom_training_error":0.0}
{"stock":"1109.XHKG_closeDelta9dR","score":1.0,"params":{"copy_X":true,"fit_intercept":true,"n_jobs":null,"normalize":false,"positive":false},"custom_training_error_sum":4.338670878e-27,"custom_training_error":0.0}
{"stock":"2007.XHKG_closeDelta8dR","score":1.0,"params":{"copy_X":true,"fit_intercept":true,"n_jobs":null,"normalize":false,"positive":false},"custom_training_error_sum":4.845184063e-27,"custom_training_error":0.0}
{"stock":"1109.XHKG_closeDelta5dR","score":1.0,"params":{"copy_X":true,"fit_intercept":true,"n_jobs":null,"normalize":false,"positive":false},"custom_training_error_sum":4.576254625e-27,"custom_training_error":0.0}
{"stock":"1928.XHKG_closeDelta9dR","score":1.0,"params":{"copy_X":true,"fit_intercept":true,"n_jobs":null,"normalize":false,"positive":false},"custom_training_error_sum":2.61369033e-27,"custom_training_error":0.0}
{"stock":"0175.XHKG_closeDelta4dR","score":1.0,"params":{"copy_X":true,"fit_intercept":true,"n_jobs":null,"normalize":false,"positive":false},"custom_training_error_sum":3.950248819e-27,"custom_training_error":0.0}
{"stock":"2238.XHKG_closeDelta7dR","score":1.0,"params":{"copy_X":true,"fit_intercept":true,"n_jobs":null,"normalize":false,"positive":false},"custom_training_error_sum":3.43166272e-27,"custom_training_error":0.0}
{"stock":"0288.XHKG_closeDelta8dR","score":1.0,"params":{"copy_X":true,"fit_intercept":true,"n_jobs":null,"normalize":false,"positive":false},"custom_training_error_sum":2.612084552e-27,"custom_training_error":0.0}
{"stock":"1972.XHKG_closeDelta9dR","score":1.0,"params":{"copy_X":true,"fit_intercept":true,"n_jobs":null,"normalize":false,"positive":false},"custom_training_error_sum":2.412800924e-27,"custom_training_error":0.0}
{"stock":"0384.XHKG_closeDelta1dR","score":1.0,"params":{"copy_X":true,"fit_intercept":true,"n_jobs":null,"normalize":false,"positive":false},"custom_training_error_sum":2.227056109e-27,"custom_training_error":0.0}
{"stock":"2328.XHKG_closeDelta1dR","score":1.0,"params":{"copy_X":true,"fit_intercept":true,"n_jobs":null,"normalize":false,"positive":false},"custom_training_error_sum":1.690674048e-27,"custom_training_error":0.0}
{"stock":"2338.XHKG_closeDelta1dR","score":1.0,"params":{"copy_X":true,"fit_intercept":true,"n_jobs":null,"normalize":false,"positive":false},"custom_training_error_sum":2.991258587e-27,"custom_training_error":0.0}
{"stock":"0006.XHKG_closeDelta6dR","score":1.0,"params":{"copy_X":true,"fit_intercept":true,"n_jobs":null,"normalize":false,"positive":false},"custom_training_error_sum":1.34567686e-27,"custom_training_error":0.0}
{"stock":"0728.XHKG_closeDelta7dR","score":1.0,"params":{"copy_X":true,"fit_intercept":true,"n_jobs":null,"normalize":false,"positive":false},"custom_training_error_sum":3.296310061e-27,"custom_training_error":0.0}
{"stock":"2601.XHKG_closeDelta6dR","score":1.0,"params":{"copy_X":true,"fit_intercept":true,"n_jobs":null,"normalize":false,"positive":false},"custom_training_error_sum":4.788541984e-27,"custom_training_error":0.0}
{"stock":"3968.XHKG_closeDelta5dR","score":1.0,"params":{"copy_X":true,"fit_intercept":true,"n_jobs":null,"normalize":false,"positive":false},"custom_training_error_sum":4.564538277e-27,"custom_training_error":0.0}
{"stock":"0003.XHKG_closeDelta8dR","score":1.0,"params":{"copy_X":true,"fit_intercept":true,"n_jobs":null,"normalize":false,"positive":false},"custom_training_error_sum":1.717656404e-27,"custom_training_error":0.0}
{"stock":"0003.XHKG_closeDelta6dR","score":1.0,"params":{"copy_X":true,"fit_intercept":true,"n_jobs":null,"normalize":false,"positive":false},"custom_training_error_sum":1.340405825e-27,"custom_training_error":0.0}
{"stock":"0001.XHKG_closeDelta8dR","score":1.0,"params":{"copy_X":true,"fit_intercept":true,"n_jobs":null,"normalize":false,"positive":false},"custom_training_error_sum":1.845472674e-27,"custom_training_error":0.0}
{"stock":"0945.XHKG_closeDelta1dR","score":1.0,"params":{"copy_X":true,"fit_intercept":true,"n_jobs":null,"normalize":false,"positive":false},"custom_training_error_sum":2.007576458e-27,"custom_training_error":0.0}
{"stock":"0390.XHKG_closeDelta6dR","score":1.0,"params":{"copy_X":true,"fit_intercept":true,"n_jobs":null,"normalize":false,"positive":false},"custom_training_error_sum":3.213712362e-27,"custom_training_error":0.0}
{"stock":"2611.XHKG_closeDelta8dR","score":1.0,"params":{"copy_X":true,"fit_intercept":true,"n_jobs":null,"normalize":false,"positive":false},"custom_training_error_sum":3.335609201e-27,"custom_training_error":0.0}
{"stock":"2378.XHKG_closeDelta1dR","score":1.0,"params":{"copy_X":true,"fit_intercept":true,"n_jobs":null,"normalize":false,"positive":false},"custom_training_error_sum":2.031183027e-27,"custom_training_error":0.0}
{"stock":"1800.XHKG_closeDelta1dR","score":1.0,"params":{"copy_X":true,"fit_intercept":true,"n_jobs":null,"normalize":false,"positive":false},"custom_training_error_sum":2.079425208e-27,"custom_training_error":0.0}
{"stock":"2378.XHKG_closeDelta6dR","score":1.0,"params":{"copy_X":true,"fit_intercept":true,"n_jobs":null,"normalize":false,"positive":false},"custom_training_error_sum":2.049442177e-27,"custom_training_error":0.0}
{"stock":"6886.XHKG_closeDelta8dR","score":1.0,"params":{"copy_X":true,"fit_intercept":true,"n_jobs":null,"normalize":false,"positive":false},"custom_training_error_sum":4.495437196e-27,"custom_training_error":0.0}
{"stock":"1038.XHKG_closeDelta1dR","score":1.0,"params":{"copy_X":true,"fit_intercept":true,"n_jobs":null,"normalize":false,"positive":false},"custom_training_error_sum":1.405147883e-27,"custom_training_error":0.0}
{"stock":"1177.XHKG_closeDelta9dR","score":1.0,"params":{"copy_X":true,"fit_intercept":true,"n_jobs":null,"normalize":false,"positive":false},"custom_training_error_sum":1.473162743e-27,"custom_training_error":0.0}
{"stock":"1336.XHKG_closeDelta5dR","score":1.0,"params":{"copy_X":true,"fit_intercept":true,"n_jobs":null,"normalize":false,"positive":false},"custom_training_error_sum":3.507657105e-27,"custom_training_error":0.0}
{"stock":"1997.XHKG_closeDelta3dR","score":1.0,"params":{"copy_X":true,"fit_intercept":true,"n_jobs":null,"normalize":false,"positive":false},"custom_training_error_sum":1.534002238e-27,"custom_training_error":0.0}
{"stock":"1088.XHKG_closeDelta3dR","score":1.0,"params":{"copy_X":true,"fit_intercept":true,"n_jobs":null,"normalize":false,"positive":false},"custom_training_error_sum":2.613978657e-27,"custom_training_error":0.0}
{"stock":"0011.XHKG_closeDelta2dR","score":1.0,"params":{"copy_X":true,"fit_intercept":true,"n_jobs":null,"normalize":false,"positive":false},"custom_training_error_sum":2.103629169e-27,"custom_training_error":0.0}
{"stock":"0011.XHKG_closeDelta3dR","score":1.0,"params":{"copy_X":true,"fit_intercept":true,"n_jobs":null,"normalize":false,"positive":false},"custom_training_error_sum":1.723028693e-27,"custom_training_error":0.0}
{"stock":"1810.XHKG_closeDelta1dR","score":1.0,"params":{"copy_X":true,"fit_intercept":true,"n_jobs":null,"normalize":false,"positive":false},"custom_training_error_sum":2.332248856e-27,"custom_training_error":0.0}
{"stock":"6837.XHKG_closeDelta1dR","score":1.0,"params":{"copy_X":true,"fit_intercept":true,"n_jobs":null,"normalize":false,"positive":false},"custom_training_error_sum":2.39115129e-27,"custom_training_error":0.0}
{"stock":"1038.XHKG_closeDelta2dR","score":1.0,"params":{"copy_X":true,"fit_intercept":true,"n_jobs":null,"normalize":false,"positive":false},"custom_training_error_sum":1.119856833e-27,"custom_training_error":0.0}
{"stock":"1336.XHKG_closeDelta8dR","score":1.0,"params":{"copy_X":true,"fit_intercept":true,"n_jobs":null,"normalize":false,"positive":false},"custom_training_error_sum":4.420138135e-27,"custom_training_error":0.0}
{"stock":"1658.XHKG_closeDelta2dR","score":1.0,"params":{"copy_X":true,"fit_intercept":true,"n_jobs":null,"normalize":false,"positive":false},"custom_training_error_sum":1.710383849e-27,"custom_training_error":0.0}
{"stock":"2388.XHKG_closeDelta3dR","score":1.0,"params":{"copy_X":true,"fit_intercept":true,"n_jobs":null,"normalize":false,"positive":false},"custom_training_error_sum":2.005490743e-27,"custom_training_error":0.0}
{"stock":"1658.XHKG_closeDelta4dR","score":1.0,"params":{"copy_X":true,"fit_intercept":true,"n_jobs":null,"normalize":false,"positive":false},"custom_training_error_sum":3.260584e-27,"custom_training_error":0.0}
{"stock":"1336.XHKG_closeDelta4dR","score":1.0,"params":{"copy_X":true,"fit_intercept":true,"n_jobs":null,"normalize":false,"positive":false},"custom_training_error_sum":3.986816941e-27,"custom_training_error":0.0}
{"stock":"2628.XHKG_closeDelta5dR","score":1.0,"params":{"copy_X":true,"fit_intercept":true,"n_jobs":null,"normalize":false,"positive":false},"custom_training_error_sum":2.150798805e-27,"custom_training_error":0.0}
{"stock":"2269.XHKG_closeDelta2dR","score":1.0,"params":{"copy_X":true,"fit_intercept":true,"n_jobs":null,"normalize":false,"positive":false},"custom_training_error_sum":3.322980599e-27,"custom_training_error":0.0}
{"stock":"1800.XHKG_closeDelta5dR","score":1.0,"params":{"copy_X":true,"fit_intercept":true,"n_jobs":null,"normalize":false,"positive":false},"custom_training_error_sum":1.090766485e-27,"custom_training_error":0.0}
{"stock":"0011.XHKG_closeDelta5dR","score":1.0,"params":{"copy_X":true,"fit_intercept":true,"n_jobs":null,"normalize":false,"positive":false},"custom_training_error_sum":1.438444159e-27,"custom_training_error":0.0}
{"stock":"1336.XHKG_closeDelta3dR","score":1.0,"params":{"copy_X":true,"fit_intercept":true,"n_jobs":null,"normalize":false,"positive":false},"custom_training_error_sum":3.656290216e-27,"custom_training_error":0.0}
{"stock":"0688.XHKG_closeDelta9dR","score":1.0,"params":{"copy_X":true,"fit_intercept":true,"n_jobs":null,"normalize":false,"positive":false},"custom_training_error_sum":4.943167071e-27,"custom_training_error":0.0}
{"stock":"1398.XHKG_closeDelta3dR","score":1.0,"params":{"copy_X":true,"fit_intercept":true,"n_jobs":null,"normalize":false,"positive":false},"custom_training_error_sum":3.679346965e-27,"custom_training_error":0.0}
{"stock":"0857.XHKG_closeDelta4dR","score":1.0,"params":{"copy_X":true,"fit_intercept":true,"n_jobs":null,"normalize":false,"positive":false},"custom_training_error_sum":2.555659829e-27,"custom_training_error":0.0}
{"stock":"3328.XHKG_closeDelta5dR","score":1.0,"params":{"copy_X":true,"fit_intercept":true,"n_jobs":null,"normalize":false,"positive":false},"custom_training_error_sum":2.554589096e-27,"custom_training_error":0.0}
{"stock":"0006.XHKG_closeDelta1dR","score":1.0,"params":{"copy_X":true,"fit_intercept":true,"n_jobs":null,"normalize":false,"positive":false},"custom_training_error_sum":1.740443643e-27,"custom_training_error":0.0}
{"stock":"0728.XHKG_closeDelta9dR","score":1.0,"params":{"copy_X":true,"fit_intercept":true,"n_jobs":null,"normalize":false,"positive":false},"custom_training_error_sum":4.658769481e-27,"custom_training_error":0.0}
{"stock":"0390.XHKG_closeDelta3dR","score":1.0,"params":{"copy_X":true,"fit_intercept":true,"n_jobs":null,"normalize":false,"positive":false},"custom_training_error_sum":1.981028752e-27,"custom_training_error":0.0}
{"stock":"2319.XHKG_closeDelta3dR","score":1.0,"params":{"copy_X":true,"fit_intercept":true,"n_jobs":null,"normalize":false,"positive":false},"custom_training_error_sum":2.57182794e-27,"custom_training_error":0.0}
{"stock":"0011.XHKG_closeDelta6dR","score":1.0,"params":{"copy_X":true,"fit_intercept":true,"n_jobs":null,"normalize":false,"positive":false},"custom_training_error_sum":1.605775848e-27,"custom_training_error":0.0}
{"stock":"1113.XHKG_closeDelta2dR","score":1.0,"params":{"copy_X":true,"fit_intercept":true,"n_jobs":null,"normalize":false,"positive":false},"custom_training_error_sum":1.550957812e-27,"custom_training_error":0.0}
{"stock":"0386.XHKG_closeDelta9dR","score":1.0,"params":{"copy_X":true,"fit_intercept":true,"n_jobs":null,"normalize":false,"positive":false},"custom_training_error_sum":2.277007133e-27,"custom_training_error":0.0}
{"stock":"1113.XHKG_closeDelta9dR","score":1.0,"params":{"copy_X":true,"fit_intercept":true,"n_jobs":null,"normalize":false,"positive":false},"custom_training_error_sum":1.816327521e-27,"custom_training_error":0.0}
{"stock":"0883.XHKG_closeDelta7dR","score":1.0,"params":{"copy_X":true,"fit_intercept":true,"n_jobs":null,"normalize":false,"positive":false},"custom_training_error_sum":2.78607001e-27,"custom_training_error":0.0}
{"stock":"2202.XHKG_closeDelta3dR","score":1.0,"params":{"copy_X":true,"fit_intercept":true,"n_jobs":null,"normalize":false,"positive":false},"custom_training_error_sum":3.454548606e-27,"custom_training_error":0.0}
{"stock":"2319.XHKG_closeDelta2dR","score":1.0,"params":{"copy_X":true,"fit_intercept":true,"n_jobs":null,"normalize":false,"positive":false},"custom_training_error_sum":2.022958042e-27,"custom_training_error":0.0}
{"stock":"1972.XHKG_closeDelta4dR","score":1.0,"params":{"copy_X":true,"fit_intercept":true,"n_jobs":null,"normalize":false,"positive":false},"custom_training_error_sum":1.672189357e-27,"custom_training_error":0.0}
{"stock":"0019.XHKG_closeDelta1dR","score":1.0,"params":{"copy_X":true,"fit_intercept":true,"n_jobs":null,"normalize":false,"positive":false},"custom_training_error_sum":2.175685888e-27,"custom_training_error":0.0}
{"stock":"1816.XHKG_closeDelta2dR","score":1.0,"params":{"copy_X":true,"fit_intercept":true,"n_jobs":null,"normalize":false,"positive":false},"custom_training_error_sum":2.237676902e-27,"custom_training_error":0.0}
{"stock":"1972.XHKG_closeDelta1dR","score":1.0,"params":{"copy_X":true,"fit_intercept":true,"n_jobs":null,"normalize":false,"positive":false},"custom_training_error_sum":1.956639427e-27,"custom_training_error":0.0}
{"stock":"2007.XHKG_closeDelta6dR","score":1.0,"params":{"copy_X":true,"fit_intercept":true,"n_jobs":null,"normalize":false,"positive":false},"custom_training_error_sum":4.392556419e-27,"custom_training_error":0.0}
{"stock":"0012.XHKG_closeDelta2dR","score":1.0,"params":{"copy_X":true,"fit_intercept":true,"n_jobs":null,"normalize":false,"positive":false},"custom_training_error_sum":1.809628033e-27,"custom_training_error":0.0}
{"stock":"2888.XHKG_closeDelta2dR","score":1.0,"params":{"copy_X":true,"fit_intercept":true,"n_jobs":null,"normalize":false,"positive":false},"custom_training_error_sum":1.868516929e-27,"custom_training_error":0.0}
{"stock":"1800.XHKG_closeDelta8dR","score":1.0,"params":{"copy_X":true,"fit_intercept":true,"n_jobs":null,"normalize":false,"positive":false},"custom_training_error_sum":4.705921072e-27,"custom_training_error":0.0}
{"stock":"2238.XHKG_closeDelta2dR","score":1.0,"params":{"copy_X":true,"fit_intercept":true,"n_jobs":null,"normalize":false,"positive":false},"custom_training_error_sum":3.601309193e-27,"custom_training_error":0.0}
{"stock":"1177.XHKG_closeDelta6dR","score":1.0,"params":{"copy_X":true,"fit_intercept":true,"n_jobs":null,"normalize":false,"positive":false},"custom_training_error_sum":1.628517074e-27,"custom_training_error":0.0}
{"stock":"1988.XHKG_closeDelta6dR","score":1.0,"params":{"copy_X":true,"fit_intercept":true,"n_jobs":null,"normalize":false,"positive":false},"custom_training_error_sum":2.773821325e-27,"custom_training_error":0.0}
{"stock":"0857.XHKG_closeDelta6dR","score":1.0,"params":{"copy_X":true,"fit_intercept":true,"n_jobs":null,"normalize":false,"positive":false},"custom_training_error_sum":1.038529989e-27,"custom_training_error":0.0}
{"stock":"2382.XHKG_closeDelta6dR","score":1.0,"params":{"copy_X":true,"fit_intercept":true,"n_jobs":null,"normalize":false,"positive":false},"custom_training_error_sum":3.273411272e-27,"custom_training_error":0.0}
{"stock":"1093.XHKG_closeDelta7dR","score":1.0,"params":{"copy_X":true,"fit_intercept":true,"n_jobs":null,"normalize":false,"positive":false},"custom_training_error_sum":2.117114649e-27,"custom_training_error":0.0}
{"stock":"6886.XHKG_closeDelta3dR","score":1.0,"params":{"copy_X":true,"fit_intercept":true,"n_jobs":null,"normalize":false,"positive":false},"custom_training_error_sum":3.880270283e-27,"custom_training_error":0.0}
{"stock":"1186.XHKG_closeDelta7dR","score":1.0,"params":{"copy_X":true,"fit_intercept":true,"n_jobs":null,"normalize":false,"positive":false},"custom_training_error_sum":3.062071242e-27,"custom_training_error":0.0}
{"stock":"1109.XHKG_closeDelta6dR","score":1.0,"params":{"copy_X":true,"fit_intercept":true,"n_jobs":null,"normalize":false,"positive":false},"custom_training_error_sum":4.83366076e-27,"custom_training_error":0.0}
{"stock":"6837.XHKG_closeDelta8dR","score":1.0,"params":{"copy_X":true,"fit_intercept":true,"n_jobs":null,"normalize":false,"positive":false},"custom_training_error_sum":5.003269065e-27,"custom_training_error":0.0}
{"stock":"1288.XHKG_closeDelta5dR","score":1.0,"params":{"copy_X":true,"fit_intercept":true,"n_jobs":null,"normalize":false,"positive":false},"custom_training_error_sum":1.274680202e-27,"custom_training_error":0.0}
{"stock":"0291.XHKG_closeDelta9dR","score":1.0,"params":{"copy_X":true,"fit_intercept":true,"n_jobs":null,"normalize":false,"positive":false},"custom_training_error_sum":2.555430318e-27,"custom_training_error":0.0}
{"stock":"0688.XHKG_closeDelta7dR","score":1.0,"params":{"copy_X":true,"fit_intercept":true,"n_jobs":null,"normalize":false,"positive":false},"custom_training_error_sum":4.087324355e-27,"custom_training_error":0.0}
{"stock":"0941.XHKG_closeDelta9dR","score":1.0,"params":{"copy_X":true,"fit_intercept":true,"n_jobs":null,"normalize":false,"positive":false},"custom_training_error_sum":2.91341093e-27,"custom_training_error":0.0}
{"stock":"2319.XHKG_closeDelta5dR","score":1.0,"params":{"copy_X":true,"fit_intercept":true,"n_jobs":null,"normalize":false,"positive":false},"custom_training_error_sum":2.654028362e-27,"custom_training_error":0.0}
{"stock":"1997.XHKG_closeDelta6dR","score":1.0,"params":{"copy_X":true,"fit_intercept":true,"n_jobs":null,"normalize":false,"positive":false},"custom_training_error_sum":1.393727726e-27,"custom_training_error":0.0}
{"stock":"0960.XHKG_closeDelta9dR","score":1.0,"params":{"copy_X":true,"fit_intercept":true,"n_jobs":null,"normalize":false,"positive":false},"custom_training_error_sum":2.073389021e-27,"custom_training_error":0.0}
{"stock":"2202.XHKG_closeDelta5dR","score":1.0,"params":{"copy_X":true,"fit_intercept":true,"n_jobs":null,"normalize":false,"positive":false},"custom_training_error_sum":3.951189467e-27,"custom_training_error":0.0}
